prefect_openmetadata/__init__.py
prefect_openmetadata/_version.py
prefect_openmetadata/flows.py
prefect_openmetadata/ingestion_workflow.py
prefect_openmetadata/profiler_workflow.py
prefect_openmetadata-0.3.0.dist-info/LICENSE
prefect_openmetadata-0.3.0.dist-info/METADATA
prefect_openmetadata-0.3.0.dist-info/WHEEL
prefect_openmetadata-0.3.0.dist-info/top_level.txt
prefect_openmetadata-0.3.0.dist-info/RECORD
