Metadata-Version: 2.1
Name: prefect-openmetadata
Version: 0.3.0
Summary: Prefect integration with OpenMetadata
Home-page: https://github.com/PrefectHQ/prefect-openmetadata
Author: prefect-openmetadata
Author-email: anna@prefect.io
License: Apache License 2.0
Keywords: prefect
Classifier: Natural Language :: English
Classifier: Intended Audience :: Developers
Classifier: Intended Audience :: System Administrators
Classifier: License :: OSI Approved :: Apache Software License
Classifier: Programming Language :: Python :: 3 :: Only
Classifier: Programming Language :: Python :: 3.8
Classifier: Programming Language :: Python :: 3.9
Classifier: Programming Language :: Python :: 3.10
Classifier: Topic :: Software Development :: Libraries
Requires-Python: >=3.8
License-File: LICENSE
Requires-Dist: prefect
Requires-Dist: openmetadata-ingestion[docker]
Provides-Extra: dev
Requires-Dist: pytest ; extra == 'dev'
Requires-Dist: black ; extra == 'dev'
Requires-Dist: flake8 ; extra == 'dev'
Requires-Dist: mypy ; extra == 'dev'
Requires-Dist: mkdocs ; extra == 'dev'
Requires-Dist: mkdocs-material ; extra == 'dev'
Requires-Dist: mkdocstrings[python] ; extra == 'dev'
Requires-Dist: isort ; extra == 'dev'
Requires-Dist: pre-commit ; extra == 'dev'
Requires-Dist: pytest-asyncio ; extra == 'dev'
Requires-Dist: mkdocs-gen-files ; extra == 'dev'
Requires-Dist: interrogate ; extra == 'dev'
Requires-Dist: coverage ; extra == 'dev'
Requires-Dist: openmetadata-ingestion ; extra == 'dev'
Requires-Dist: mock ; (python_version < "3.8") and extra == 'dev'
